verispy/__init__.py
verispy/veris.py
verispy/tests/__init__.py
verispy/tests/test_veris.py
verispy/tests/data/0008DADB-E83D-4278-A19A-CEE01610CF43.json
verispy/tests/data/011E42B7-DF7F-4D2E-BB85-24A0DD159C64.json
verispy/tests/data/01A00ECE-E4DB-4AA1-A5AE-8F326D76A9A5.json
verispy/tests/data/0688C151-440A-4754-A5D9-8B4CF7527877.json
verispy/tests/data/06D9796B-8E23-48C8-8C28-0C67544BFF7A.json
verispy/tests/data/06EEA2A7-6CCC-4EB0-AF24-133E74851E08.json
verispy/tests/data/082994AF-C81C-49CB-B18C-F41A8413929A.json
verispy/tests/data/0B385BB0-8E64-4F5E-9BC4-EABA874B5BAA.json
verispy/tests/data/1003F66F-2557-4FCE-A726-4A1652D52283.json
verispy/tests/data/10907CF2-6668-4188-80C3-D199D8B777CE.json
verispy/tests/data/139B8366-B311-4B18-B43C-86CA43B226C6.json
verispy/tests/data/192AE6B9-535F-4760-839E-BFC39BBD0FB8.json
verispy/tests/data/1A9DD279-9F16-44CE-B932-8A40F18FE811.json
verispy/tests/data/1BEB19CD-C396-43AB-BC1B-6EB443F76EB2.json
verispy/tests/data/20fd3ba0-6a5d-4093-b301-4d03dce43343.json
verispy/tests/data/252051da-d52a-4893-acb3-3867bca5c492.json
verispy/tests/data/25259B3D-9543-4F88-9EDB-E75DCC92B84D.json
verispy/tests/data/27A53617-0630-4822-BC0C-114ABDA69AB6.json
verispy/tests/data/29F53611-1587-4061-94FD-5951C643174E.json
verispy/tests/data/2BA16C38-6E85-4106-9556-A48FC78A59CA.json
verispy/tests/data/2D7227C5-E384-4745-A96F-B33F2042BDA6.json
verispy/tests/data/2D78818E-CE5E-4E22-A545-1E08C9897C20.json
verispy/tests/data/2FBA39C9-1207-40F5-8D0D-6FF4C5616CF6.json
verispy/tests/data/30A22965-C181-48DB-B125-4FFB0318FFDD.json
verispy/tests/data/32F4DDA3-EEBC-40B2-8815-A30CD20C35EA.json
verispy/tests/data/33F98FAB-6D50-42D7-9B85-2CA264764FAD.json
verispy/tests/data/3564313A-9AB9-46CC-B7E8-F07A367D42E6.json
verispy/tests/data/36397D15-D194-48AC-924B-247419F5FD0F.json
verispy/tests/data/37DE7C25-598B-4DD4-9AF1-D3980BC5BD8D.json
verispy/tests/data/37ECDB58-2231-498D-BB8C-4CC314B36A10.json
verispy/tests/data/3A417236-25F9-4EB4-9791-B7D1BDF9A0E8.json
verispy-0.1.13.dist-info/LICENSE
verispy-0.1.13.dist-info/METADATA
verispy-0.1.13.dist-info/WHEEL
verispy-0.1.13.dist-info/top_level.txt
verispy-0.1.13.dist-info/RECORD
