Metadata-Version: 2.1
Name: verispy
Version: 0.1.13
Summary: Parses VCDB json data into a Pandas DataFrame and provides summary functions and basic enumeration plotting.
Home-page: https://github.com/RiskLens/verispy
Author: Tyler Byers
Author-email: tbyers@risklens.com
License: MIT
Platform: UNKNOWN
Classifier: Programming Language :: Python :: 3
Classifier: License :: OSI Approved :: MIT License
Classifier: Operating System :: OS Independent
Requires-Dist: numpy (>=1.18.1)
Requires-Dist: pytest (>=5.4.3)
Requires-Dist: statsmodels (>=0.11.1)
Requires-Dist: matplotlib (>=3.2.1)
Requires-Dist: pandas (>=1.0.4)
Requires-Dist: tqdm (>=4.46.0)
Requires-Dist: requests (>=2.23.0)
